nonebot_plugin_aising/__init__.py
nonebot_plugin_aising-0.1.5.dist-info/LICENSE
nonebot_plugin_aising-0.1.5.dist-info/METADATA
nonebot_plugin_aising-0.1.5.dist-info/WHEEL
nonebot_plugin_aising-0.1.5.dist-info/RECORD
