Metadata-Version: 2.1
Name: nonebot-plugin-aising
Version: 0.1.5
Summary: 能让b站任何能搜到素材的角色唱歌
Home-page: https://github.com/CCYellowStar2/nonebot-plugin-aising
License: GPL-3.0-only
Author: CCYellowStar
Requires-Python: >=3.9,<4
Classifier: License :: OSI Approved :: GNU General Public License v3 (GPLv3)
Classifier: Programming Language :: Python :: 3
Classifier: Programming Language :: Python :: 3.9
Classifier: Programming Language :: Python :: 3.10
Classifier: Programming Language :: Python :: 3.11
Classifier: Programming Language :: Python :: 3.12
Requires-Dist: gradio_client (>=0.16.4,<0.17.0)
Requires-Dist: nonebot-adapter-onebot (>=2.2.3)
Requires-Dist: nonebot2 (>=2.2.1)
Requires-Dist: nonebot_plugin_localstore (>=0.4.1)
Project-URL: Repository, https://github.com/CCYellowStar2/nonebot-plugin-aising
